TKEanalyst/__init__.py
TKEanalyst/config.py
TKEanalyst/flowstat.py
TKEanalyst/profile_analyst.py
TKEanalyst/profile_plotter.py
TKEanalyst/rmspike.py
TKEanalyst-1.0.3.dist-info/LICENSE
TKEanalyst-1.0.3.dist-info/METADATA
TKEanalyst-1.0.3.dist-info/WHEEL
TKEanalyst-1.0.3.dist-info/top_level.txt
TKEanalyst-1.0.3.dist-info/RECORD
