Metadata-Version: 2.1
Name: TKEanalyst
Version: 1.0.3
Summary: Analyze turbulent kinetic energy from ADV measurements
Home-page: https://TKEanalyst.readthedocs.io/
Author: sschwindt
Author-email: schwindt.water@gmail.com
License: BSD License
Project-URL: Documentation, https://TKEanalyst.readthedocs.io/
Project-URL: Funding, https://hydro-informatics.com/
Project-URL: Source, https://github.com/sschwindt/TKEanalyst
Project-URL: Tracker, https://github.com/sschwindt/TKEanalyst/issues
Keywords: acoustic doppler velocimetry,ADV,Vectrino,turbulent kinetic energy,spikes,despiking
Platform: UNKNOWN
Classifier: License :: OSI Approved :: BSD License
Classifier: Operating System :: OS Independent
Classifier: Development Status :: 4 - Beta
Classifier: Programming Language :: Python
Classifier: Programming Language :: Python :: 3
Classifier: Programming Language :: Python :: 3.6
Classifier: Programming Language :: Python :: 3.7
Classifier: Programming Language :: Python :: 3.8
Classifier: Programming Language :: Python :: 3.9
Classifier: Programming Language :: Python :: Implementation :: CPython
Classifier: Programming Language :: Python :: Implementation :: PyPy
Requires-Python: >=3.6.0
Requires-Dist: matplotlib
Requires-Dist: numpy
Requires-Dist: openpyxl
Requires-Dist: pandas
